relkit/__init__.py
relkit/__main__.py
relkit/checks/__init__.py
relkit/checks/changelog.py
relkit/checks/distribution.py
relkit/checks/git.py
relkit/checks/hooks.py
relkit/checks/quality.py
relkit/checks/version.py
relkit/cli.py
relkit/commands/__init__.py
relkit/commands/build.py
relkit/commands/bump.py
relkit/commands/changelog.py
relkit/commands/check.py
relkit/commands/git.py
relkit/commands/init_hooks.py
relkit/commands/preflight.py
relkit/commands/publish.py
relkit/commands/release.py
relkit/commands/status.py
relkit/commands/test.py
relkit/commands/version.py
relkit/constants.py
relkit/decorators.py
relkit/models.py
relkit/safety.py
relkit/utils.py
relkit/workflows.py
relkit/workspace.py
relkit-1.5.5.dist-info/WHEEL
relkit-1.5.5.dist-info/entry_points.txt
relkit-1.5.5.dist-info/METADATA
relkit-1.5.5.dist-info/RECORD
