Metadata-Version: 2.3
Name: relkit
Version: 1.5.5
Summary: Opinionated release toolkit for modern Python projects
Keywords: release,workflow,changelog,versioning,monorepo,automation
Author: Fredrik Angelsen
Author-email: Fredrik Angelsen <fredrikangelsen@gmail.com>
License: MIT
Classifier: Development Status :: 4 - Beta
Classifier: Programming Language :: Python :: 3.12
Classifier: License :: OSI Approved :: MIT License
Classifier: Intended Audience :: Developers
Classifier: Topic :: Software Development :: Build Tools
Requires-Python: >=3.12
